{
  "boards": [
    {
      "username": "blah",
      "board": {
        "boardContent": [
          "Select Golfer",
          "Select Golfer",
          "Select Golfer",
          "Select Golfer",
          "Select Golfer",
          "Select Golfer",
          "Select Golfer",
          "Select Golfer",
          "Select Golfer",
          "Select Golfer",
          "Select Golfer",
          "Select Golfer",
          {
            "name": "Xander Schauffele",
            "salary": 11800
          },
          "Select Golfer",
          "Select Golfer",
          "Select Golfer",
          "Select Golfer",
          "Select Golfer",
          "Select Golfer",
          "Select Golfer",
          "Select Golfer",
          "Select Golfer",
          "Select Golfer",
          "Select Golfer",
          "Select Golfer"
        ],
        "selectedSquares": [],
        "usedGolfers": [
          "Xander Schauffele"
        ],
        "lastSaved": "2025-07-08T19:25:00.951Z"
      }
    },
    {
      "username": "justinjfry",
      "board": {
        "boardContent": [
          "Select Golfer",
          "Select Golfer",
          "Select Golfer",
          "Select Golfer",
          "Select Golfer",
          "Select Golfer",
          "Select Golfer",
          "Select Golfer",
          "Select Golfer",
          "Select Golfer",
          "Select Golfer",
          {
            "name": "Ludvig Aberg",
            "salary": 11500
          },
          "Select Golfer",
          "Select Golfer",
          "Select Golfer",
          "Select Golfer",
          "Select Golfer",
          "Select Golfer",
          "Select Golfer",
          "Select Golfer",
          "Select Golfer",
          "Select Golfer",
          "Select Golfer",
          "Select Golfer",
          "Select Golfer"
        ],
        "selectedSquares": [],
        "usedGolfers": [
          "Ludvig Aberg"
        ],
        "lastSaved": "2025-07-08T19:42:36.705Z"
      }
    },
    {
      "username": "test",
      "board": {
        "boardContent": [
          "Select Golfer",
          "Select Golfer",
          "Select Golfer",
          "Select Golfer",
          "Select Golfer",
          "Select Golfer",
          "Select Golfer",
          "Select Golfer",
          "Select Golfer",
          "Select Golfer",
          "Select Golfer",
          {
            "name": "Ludvig Aberg",
            "salary": 11500
          },
          "Select Golfer",
          "Select Golfer",
          "Select Golfer",
          "Select Golfer",
          "Select Golfer",
          {
            "name": "Patrick Cantlay",
            "salary": 11400
          },
          "Select Golfer",
          "Select Golfer",
          "Select Golfer",
          "Select Golfer",
          "Select Golfer",
          "Select Golfer",
          {
            "name": "Viktor Hovland",
            "salary": 11000
          }
        ],
        "selectedSquares": [
          11
        ],
        "usedGolfers": [
          "Ludvig Aberg",
          "Viktor Hovland",
          "Patrick Cantlay"
        ],
        "lastSaved": "2025-07-08T19:47:03.241Z"
      }
    },
    {
      "username": "bob",
      "board": {
        "boardContent": [
          "Select Golfer",
          "Select Golfer",
          "Select Golfer",
          "Select Golfer",
          "Select Golfer",
          "Select Golfer",
          "Select Golfer",
          "Select Golfer",
          "Select Golfer",
          "Select Golfer",
          "Select Golfer",
          {
            "name": "Ludvig Aberg",
            "salary": 11500
          },
          "Select Golfer",
          "Select Golfer",
          "Select Golfer",
          "Select Golfer",
          "Select Golfer",
          "Select Golfer",
          "Select Golfer",
          "Select Golfer",
          "Select Golfer",
          "Select Golfer",
          "Select Golfer",
          "Select Golfer",
          "Select Golfer"
        ],
        "selectedSquares": [],
        "usedGolfers": [
          "Ludvig Aberg"
        ],
        "lastSaved": "2025-07-08T19:47:21.794Z"
      }
    },
    {
      "username": "joe",
      "board": {
        "boardContent": [
          "Select Golfer",
          "Select Golfer",
          "Select Golfer",
          "Select Golfer",
          "Select Golfer",
          "Select Golfer",
          "Select Golfer",
          "Select Golfer",
          "Select Golfer",
          "Select Golfer",
          "Select Golfer",
          "Select Golfer",
          {
            "name": "Scottie Scheffler",
            "salary": 13600
          },
          {
            "name": "Xander Schauffele",
            "salary": 11800
          },
          {
            "name": "Collin Morikawa",
            "salary": 11600
          },
          "Select Golfer",
          "Select Golfer",
          "Select Golfer",
          "Select Golfer",
          "Select Golfer",
          "Select Golfer",
          "Select Golfer",
          "Select Golfer",
          "Select Golfer",
          "Select Golfer"
        ],
        "selectedSquares": [],
        "usedGolfers": [
          "Scottie Scheffler",
          "Xander Schauffele",
          "Collin Morikawa"
        ],
        "lastSaved": "2025-07-10T18:58:57.605Z"
      }
    },
    {
      "username": "billy",
      "board": {
        "boardContent": [
          "Select Golfer",
          "Select Golfer",
          "Select Golfer",
          "Select Golfer",
          "Select Golfer",
          "Select Golfer",
          {
            "name": "Viktor Hovland",
            "salary": 11000
          },
          "Select Golfer",
          "Select Golfer",
          "Select Golfer",
          "Select Golfer",
          "Select Golfer",
          {
            "name": "Patrick Cantlay",
            "salary": 11400
          },
          "Select Golfer",
          "Select Golfer",
          "Select Golfer",
          "Select Golfer",
          "Select Golfer",
          {
            "name": "Justin Thomas",
            "salary": 11200
          },
          "Select Golfer",
          "Select Golfer",
          "Select Golfer",
          "Select Golfer",
          "Select Golfer",
          "Select Golfer"
        ],
        "selectedSquares": [],
        "usedGolfers": [
          "Patrick Cantlay",
          "Justin Thomas",
          "Viktor Hovland"
        ],
        "lastSaved": "2025-07-10T18:59:54.145Z"
      }
    }
  ]
}